{"tickets":[{"id":"171d834c-f149-46a3-aaca-e26e5f966726","title":"monitor","description":"lavar o banheiro bem lavado","createdAt":"2024-12-10T20:01:16.520Z","updatedAt":"2024-12-10T21:00:35.190Z","completed_at":null},{"id":"3b09beb7-5ca2-4c14-b56e-ddc8e6ae6600","title":"fazer hoje","description":"lavar o banheiro bem lavado","createdAt":"2024-12-10T20:59:36.249Z","updatedAt":"2024-12-10T20:59:36.249Z","completed_at":null},{"id":"5b2b553f-3ae0-49f4-ba3d-8e248d448081","title":"fazer hoje","description":"lavar o banheiro bem lavado","createdAt":"2024-12-10T20:59:37.895Z","updatedAt":"2024-12-10T20:59:37.895Z","completed_at":null}]}